flask_expects_json/__init__.py
flask_expects_json/default_validator.py
flask_expects_json-1.5.0.dist-info/LICENSE.txt
flask_expects_json-1.5.0.dist-info/METADATA
flask_expects_json-1.5.0.dist-info/WHEEL
flask_expects_json-1.5.0.dist-info/top_level.txt
flask_expects_json-1.5.0.dist-info/RECORD
