Metadata-Version: 2.1
Name: flask-expects-json
Version: 1.5.0
Summary: Decorator for REST endpoints in flask. Validate JSON request data.
Home-page: https://github.com/fischerfredl/flask-expects-json
Author: Alfred Melch
Author-email: dev@melch.pro
License: MIT
Keywords: flask,json,validation,schema,jsonschema
Platform: UNKNOWN
Classifier: Framework :: Flask
Classifier: License :: OSI Approved :: MIT License
Classifier: Programming Language :: Python :: 2.7
Classifier: Programming Language :: Python :: 3.5
Classifier: Programming Language :: Python :: 3.6
